folder_tree_lister/__init__.py
folder_tree_lister/tree_listing.py
folder_tree_lister-0.0.5.dist-info/LICENSE
folder_tree_lister-0.0.5.dist-info/METADATA
folder_tree_lister-0.0.5.dist-info/WHEEL
folder_tree_lister-0.0.5.dist-info/top_level.txt
folder_tree_lister-0.0.5.dist-info/RECORD
