Metadata-Version: 2.1
Name: folder-tree-lister
Version: 0.0.5
Summary: /README.md
Home-page: https://github.com/yourusername/folder_tree_lister
Author: Dikshyant
Author-email: dikshyant180@gmail.com
Classifier: Programming Language :: Python :: 3
Classifier: Operating System :: OS Independent
Requires-Python: >=3.6
License-File: LICENSE
